wl_ai_manager/__init__.py
wl_ai_manager/ai_manager.py
wl_ai_manager/chat.py
wl_ai_manager/image_generation.py
wl_ai_manager/music_generation.py
wl_ai_manager/openai.py
wl_ai_manager/prompts.py
wl_ai_manager/schema_validator.py
wl_ai_manager/text_to_speech.py
wl_ai_manager/transcribe.py
wl_ai_manager/video_generation.py
wl_ai_manager-0.1.37.dist-info/LICENSE
wl_ai_manager-0.1.37.dist-info/METADATA
wl_ai_manager-0.1.37.dist-info/WHEEL
wl_ai_manager-0.1.37.dist-info/top_level.txt
wl_ai_manager-0.1.37.dist-info/RECORD
