Metadata-Version: 2.1
Name: wl_ai_manager
Version: 0.1.37
Summary: Python module providing unified access to OpenAI's chat, text-to-speech, and transcription APIs
Home-page: https://github.com/watkinslabs/ai_manager
Author: Chris Watkins
Author-email: chris@watkinslabs.com
Classifier: Development Status :: 3 - Alpha
Classifier: Intended Audience :: Developers
Classifier: License :: OSI Approved :: BSD License
Classifier: Operating System :: OS Independent
Classifier: Programming Language :: Python :: 3
Classifier: Programming Language :: Python :: 3.8
Classifier: Programming Language :: Python :: 3.9
Classifier: Programming Language :: Python :: 3.10
Classifier: Programming Language :: Python :: 3.11
Classifier: Programming Language :: Python :: 3.12
Classifier: Topic :: Software Development :: Libraries :: Python Modules
Classifier: Topic :: Multimedia :: Sound/Audio :: Speech
Classifier: Topic :: Scientific/Engineering :: Artificial Intelligence
Requires-Python: >=3.8
License-File: LICENSE
Requires-Dist: openai >=1.0.0
Requires-Dist: soundfile >=0.12.0
Requires-Dist: requests >=2.25.0
Requires-Dist: jsonschema
Requires-Dist: replicate
Requires-Dist: soundfile
Requires-Dist: pillow
Provides-Extra: dev
Requires-Dist: pytest >=6.0 ; extra == 'dev'
Requires-Dist: black >=22.0 ; extra == 'dev'
Requires-Dist: flake8 >=4.0 ; extra == 'dev'
